bracket_expansion.py
bracket_expansion-1.0.0.dist-info/LICENSE
bracket_expansion-1.0.0.dist-info/METADATA
bracket_expansion-1.0.0.dist-info/WHEEL
bracket_expansion-1.0.0.dist-info/top_level.txt
bracket_expansion-1.0.0.dist-info/RECORD
